binance_asyncio/__init__.py
binance_asyncio/endpoints.py
binance_asyncio/requests.py
binance_asyncio/websockets/__init__.py
binance_asyncio/websockets/streams.py
binance_asyncio-0.2.1.dist-info/licenses/LICENSE
examples/__init__.py
examples/get_klines.py
examples/orders.py
examples/socket_kline.py
examples/socket_ticker_example.py
examples/testnet_account.py
binance_asyncio-0.2.1.dist-info/METADATA
binance_asyncio-0.2.1.dist-info/WHEEL
binance_asyncio-0.2.1.dist-info/top_level.txt
binance_asyncio-0.2.1.dist-info/RECORD
