Metadata-Version: 2.4
Name: binance-asyncio
Version: 0.2.1
Summary: Library for interacting with the Binance API
Home-page: https://github.com/justdanyul/binance-asyncio
Author: Daniel Kirkegaard Mouritsen
Author-email: daniel.mouritsen@gmail.com
Classifier: Programming Language :: Python :: 3
Classifier: License :: OSI Approved :: MIT License
Classifier: Operating System :: OS Independent
Requires-Python: >=3.9
License-File: LICENSE
Requires-Dist: websockets
Requires-Dist: aiohttp
Requires-Dist: dateparser
Dynamic: author
Dynamic: author-email
Dynamic: classifier
Dynamic: description
Dynamic: description-content-type
Dynamic: home-page
Dynamic: license-file
Dynamic: requires-dist
Dynamic: requires-python
Dynamic: summary
